<?xml version="1.0" encoding="UTF-8"?>
<!--suppress ALL -->
<beans xmlns="http://www.springframework.org/schema/beans"
       xmlns:xsi="http://www.w3.org/2001/XMLSchema-instance"
       xsi:schemaLocation="http://www.springframework.org/schema/beans http://www.springframework.org/schema/beans/spring-beans.xsd">

    <bean id="user" class="com.jt.pojo.User">
        <property name="id" value="10"></property>
        <property name="name">
        <value><![CDATA[<范冰冰>]]></value>
        </property>
    </bean>
    <bean id="useraDao" class="com.jt.dao.UserDaoImpl"></bean>
    <bean id="userService" class="com.jt.service.UserServiceImpl">
        <property name="userdao" ref="useraDao"></property>
    </bean>
    <bean id="userController" class="com.jt.controller.UserController">
        <property name="userService" ref="userService"></property>
        <property name="user" ref="user"></property>
    </bean>


</beans>